{"Plot": "The birth of modern stand-up comedy began in the Catskill Mountains - a boot camp for the greatest generation of Jewish-American comedians.", "Rated": "N/A", "tomatoImage": "rotten", "Title": "When Comedy Went to School", "DVD": "17 Nov 2014", "tomatoMeter": "53", "Writer": "Lawrence Richards (conceived by), Lawrence Richards", "tomatoUserRating": "3.4", "Production": "International Film Circuit", "Actors": "Robert Klein, Jerry Lewis, Sid Caesar, Jackie Mason", "tomatoFresh": "18", "Type": "movie", "imdbVotes": "69", "Website": "http://www.whencomedywenttoschool.com/", "tomatoConsensus": "N/A", "Poster": "http://ia.media-imdb.com/images/M/MV5BMjIyNDYwNDE5N15BMl5BanBnXkFtZTcwODQ2MDc4OQ@@._V1_SX300.jpg", "tomatoRotten": "16", "Director": "Mevlut Akkaya, Ron Frank", "Released": "06 Jun 2013", "tomatoUserReviews": "428", "Awards": "N/A", "Genre": "Documentary, Comedy", "tomatoUserMeter": "48", "imdbRating": "6.1", "Language": "English", "Country": "USA", "BoxOffice": "$0.4M", "Runtime": "83 min", "tomatoReviews": "34", "imdbID": "tt2167056", "Metascore": "49", "Response": "True", "tomatoURL": "http://www.rottentomatoes.com/m/when_comedy_went_to_school/", "tomatoRating": "5.8", "Year": "2013"}