{"Plot": "In order to keep the woman of his dreams from falling for another guy, Charlie Logan has to break the curse that has made him wildly popular with single women: Sleep with Charlie once, and the next man you meet will be your true love.", "Rated": "R", "tomatoImage": "rotten", "Title": "Good Luck Chuck", "DVD": "15 Jan 2008", "tomatoMeter": "5", "Writer": "Josh Stolberg (screenplay), Steve Glenn (short story)", "tomatoUserRating": "3.2", "Production": "Lionsgate Films", "Actors": "Connor Price, Troy Gentile, Mackenzie Mowat, Sasha Pieterse", "tomatoFresh": "6", "Type": "movie", "imdbVotes": "73,766", "Website": "http://www.lionsgate.com/goodluckchuck", "tomatoConsensus": "A shortage of laughs and an undercurrent of mean-spiritedness undermine Good Luck Chuck, squandering a decent premise on gross-out humor and shopworn slapstick.", "Poster": "http://ia.media-imdb.com/images/M/MV5BMTIwMTI1MTQzM15BMl5BanBnXkFtZTcwOTgwNjM1MQ@@._V1_SX300.jpg", "tomatoRotten": "107", "Director": "Mark Helfrich", "Released": "21 Sep 2007", "tomatoUserReviews": "318655", "Awards": "1 win & 3 nominations.", "Genre": "Comedy, Romance", "tomatoUserMeter": "57", "imdbRating": "5.6", "Language": "English", "Country": "USA, Canada", "BoxOffice": "$35.0M", "Runtime": "96 min", "tomatoReviews": "113", "imdbID": "tt0452625", "Metascore": "19", "Response": "True", "tomatoURL": "http://www.rottentomatoes.com/m/good_luck_chuck/", "tomatoRating": "2.8", "Year": "2007"}