{"Plot": "A divorced woman who decides to pursue the man she's interested in learns he's her new friend's ex-husband.", "Rated": "PG-13", "tomatoImage": "certified", "Title": "Enough Said", "DVD": "14 Jan 2014", "tomatoMeter": "96", "Writer": "Nicole Holofcener", "tomatoUserRating": "3.7", "Production": "s", "Actors": "Julia Louis-Dreyfus, Lennie Loftin, Jessica St. Clair, Christopher Nicholas Smith", "tomatoFresh": "159", "Type": "movie", "imdbVotes": "48,197", "Website": "http://www.foxsearchlight.com/enoughsaid/", "tomatoConsensus": "Wryly charming, impeccably acted, and ultimately quite bittersweet, Enough Said is a grown-up movie in the best possible way.", "Poster": "http://ia.media-imdb.com/images/M/MV5BMjI2MjIwMDk2Ml5BMl5BanBnXkFtZTcwNTQ1MzQ5OQ@@._V1_SX300.jpg", "tomatoRotten": "7", "Director": "Nicole Holofcener", "Released": "11 Oct 2013", "tomatoUserReviews": "42471", "Awards": "Nominated for 1 Golden Globe. Another 9 wins & 36 nominations.", "Genre": "Comedy, Drama, Romance", "tomatoUserMeter": "75", "imdbRating": "7.1", "Language": "English", "Country": "USA", "BoxOffice": "$17.5M", "Runtime": "93 min", "tomatoReviews": "166", "imdbID": "tt2390361", "Metascore": "78", "Response": "True", "tomatoURL": "http://www.rottentomatoes.com/m/enough_said_2013/", "tomatoRating": "7.7", "Year": "2013"}