{"Plot": "When a blonde sorority queen is dumped by her boyfriend, she decides to follow him to law school to get him back and, once there, learns she has more legal savvy than she ever imagined.", "Rated": "PG-13", "tomatoImage": "N/A", "Title": "Legally Blonde", "DVD": "31 Jan 2006", "tomatoMeter": "N/A", "Writer": "Amanda Brown (novel), Karen McCullah (screenplay), Kirsten Smith (screenplay)", "tomatoUserRating": "3.4", "Production": "N/A", "Actors": "Reese Witherspoon, Luke Wilson, Selma Blair, Matthew Davis", "tomatoFresh": "N/A", "Type": "movie", "imdbVotes": "127,291", "Website": "N/A", "tomatoConsensus": "N/A", "Poster": "http://ia.media-imdb.com/images/M/MV5BNTEyNjUwMTkxMV5BMl5BanBnXkFtZTcwNjk0NDk0NA@@._V1_SX300.jpg", "tomatoRotten": "N/A", "Director": "Robert Luketic", "Released": "13 Jul 2001", "tomatoUserReviews": "482", "Awards": "Nominated for 2 Golden Globes. Another 6 wins & 10 nominations.", "Genre": "Comedy, Romance", "tomatoUserMeter": "52", "imdbRating": "6.2", "Language": "English", "Country": "USA", "BoxOffice": "N/A", "Runtime": "96 min", "tomatoReviews": "N/A", "imdbID": "tt0250494", "Metascore": "59", "Response": "True", "tomatoURL": "http://www.rottentomatoes.com/m/1155861-blonde/", "tomatoRating": "N/A", "Year": "2001"}