{"Plot": "After two of the devil's three sons escape Hell to wreak havoc on Earth, the devil must send his third son, the mild-mannered Nicky, to bring them back before it's too late.", "Rated": "PG-13", "tomatoImage": "rotten", "Title": "Little Nicky", "DVD": "24 Apr 2001", "tomatoMeter": "22", "Writer": "Tim Herlihy, Adam Sandler, Steven Brill", "tomatoUserRating": "3.0", "Production": "New Line Cinema", "Actors": "Adam Sandler, Patricia Arquette, Harvey Keitel, Rhys Ifans", "tomatoFresh": "25", "Type": "movie", "imdbVotes": "79,430", "Website": "http://www.littlenicky.com", "tomatoConsensus": "Despite the presence of a large, talented cast, the jokes in Little Nicky are dumb, tasteless, and not that funny, and Adam Sandler's character is grating to watch.", "Poster": "http://ia.media-imdb.com/images/M/MV5BMTQ4MTk3Mzk5NV5BMl5BanBnXkFtZTYwMTQ3NzI3._V1_SX300.jpg", "tomatoRotten": "90", "Director": "Steven Brill", "Released": "10 Nov 2000", "tomatoUserReviews": "459918", "Awards": "7 nominations.", "Genre": "Comedy, Fantasy", "tomatoUserMeter": "56", "imdbRating": "5.3", "Language": "English", "Country": "USA", "BoxOffice": "$38.5M", "Runtime": "90 min", "tomatoReviews": "115", "imdbID": "tt0185431", "Metascore": "38", "Response": "True", "tomatoURL": "http://www.rottentomatoes.com/m/little_nicky/", "tomatoRating": "3.9", "Year": "2000"}