{"Plot": "An investigation of sharks' importance to ecosystems and humankind's mass destruction of shark species worldwide.", "Rated": "PG", "tomatoImage": "fresh", "Title": "Sharkwater", "DVD": "08 Apr 2008", "tomatoMeter": "79", "Writer": "Rob Stewart", "tomatoUserRating": "4.2", "Production": "Freestyle Releasing", "Actors": "Patrick Moore, Erich Ritter, Rob Stewart, Paul Watson", "tomatoFresh": "31", "Type": "movie", "imdbVotes": "4,029", "Website": "http://www.sharkwater.com/", "tomatoConsensus": "In addition to its breathtaking underwater photography, Sharkwater has a convincing, impassioned argument of how the plight of sharks affects everyone.", "Poster": "http://ia.media-imdb.com/images/M/MV5BMTM2NjI2MDkyNV5BMl5BanBnXkFtZTcwMjcyNTE0MQ@@._V1_SX300.jpg", "tomatoRotten": "8", "Director": "Rob Stewart", "Released": "02 Nov 2007", "tomatoUserReviews": "4152", "Awards": "13 wins & 3 nominations.", "Genre": "Documentary", "tomatoUserMeter": "88", "imdbRating": "8.0", "Language": "English", "Country": "Canada", "BoxOffice": "N/A", "Runtime": "89 min", "tomatoReviews": "39", "imdbID": "tt0856008", "Metascore": "59", "Response": "True", "tomatoURL": "http://www.rottentomatoes.com/m/sharkwater/", "tomatoRating": "6.4", "Year": "2006"}