{"Plot": "Boxer Rocky Graziano's biopic, based on his autobiography, from childhood to his World Middleweight Championship title win at age 28 in 1947.", "Rated": "PASSED", "tomatoImage": "fresh", "Title": "Somebody Up There Likes Me", "DVD": "14 Nov 2006", "tomatoMeter": "82", "Writer": "Ernest Lehman (screenplay), Rocky Graziano (autobiography), Rowland Barber (with)", "tomatoUserRating": "3.9", "Production": "MGM Home Entertainment", "Actors": "Paul Newman, Pier Angeli, Everett Sloane, Eileen Heckart", "tomatoFresh": "9", "Type": "movie", "imdbVotes": "5,627", "Website": "N/A", "tomatoConsensus": "N/A", "Poster": "http://ia.media-imdb.com/images/M/MV5BMjAzNzAxMjg5MF5BMl5BanBnXkFtZTYwNzY4NjI2._V1_SX300.jpg", "tomatoRotten": "2", "Director": "Robert Wise", "Released": "12 Dec 1956", "tomatoUserReviews": "2359", "Awards": "Won 2 Oscars. Another 2 wins & 4 nominations.", "Genre": "Biography, Drama, Sport", "tomatoUserMeter": "87", "imdbRating": "7.5", "Language": "English", "Country": "USA", "BoxOffice": "N/A", "Runtime": "113 min", "tomatoReviews": "11", "imdbID": "tt0049778", "Metascore": "N/A", "Response": "True", "tomatoURL": "http://www.rottentomatoes.com/m/somebody_up_there_likes_me/", "tomatoRating": "6.6", "Year": "1956"}