{"Plot": "A romantic drama about a Chicago librarian with a gene that causes him to involuntarily time travel, and the complications it creates for his marriage.", "Rated": "PG-13", "tomatoImage": "rotten", "Title": "The Time Traveler's Wife", "DVD": "09 Feb 2010", "tomatoMeter": "38", "Writer": "Bruce Joel Rubin (screenplay), Audrey Niffenegger (novel)", "tomatoUserRating": "3.0", "Production": "Warner Bros. Pictures", "Actors": "Michelle Nolden, Alex Ferris, Arliss Howard, Eric Bana", "tomatoFresh": "59", "Type": "movie", "imdbVotes": "112,355", "Website": "http://www.thetimetravelerswifemovie.com/", "tomatoConsensus": "Though it may satisfy fans of the novel, The Time Traveler's Wife's plot contrivances and illogical narrative hamper its big screen effectiveness.", "Poster": "http://ia.media-imdb.com/images/M/MV5BMTU0MzkzNzg0Nl5BMl5BanBnXkFtZTcwNzUwNzQ2Mg@@._V1_SX300.jpg", "tomatoRotten": "98", "Director": "Robert Schwentke", "Released": "14 Aug 2009", "tomatoUserReviews": "982631", "Awards": "1 win & 5 nominations.", "Genre": "Drama, Fantasy, Romance", "tomatoUserMeter": "59", "imdbRating": "7.1", "Language": "English", "Country": "USA", "BoxOffice": "$63.4M", "Runtime": "107 min", "tomatoReviews": "157", "imdbID": "tt0452694", "Metascore": "47", "Response": "True", "tomatoURL": "http://www.rottentomatoes.com/m/time_travelers_wife/", "tomatoRating": "5.1", "Year": "2009"}