{"Plot": "An adaptation of the cult memoir of game show impresario Chuck Barris, in which he purports to have been a CIA hitman.", "Rated": "R", "tomatoImage": "certified", "Title": "Confessions of a Dangerous Mind", "DVD": "09 Sep 2003", "tomatoMeter": "79", "Writer": "Chuck Barris (book), Charlie Kaufman (screenplay)", "tomatoUserRating": "3.4", "Production": "Miramax Films", "Actors": "Dick Clark, Sam Rockwell, Michelle Sweeney, Drew Barrymore", "tomatoFresh": "126", "Type": "movie", "imdbVotes": "70,661", "Website": "http://www.miramax.com/confessions/index.html", "tomatoConsensus": "Rockwell is spot-on as Barris, and Clooney directs with entertaining style and flair.", "Poster": "http://ia.media-imdb.com/images/M/MV5BMTQyOTMxNjc5NF5BMl5BanBnXkFtZTYwMDk5OTg2._V1_SX300.jpg", "tomatoRotten": "33", "Director": "George Clooney", "Released": "24 Jan 2003", "tomatoUserReviews": "58322", "Awards": "7 wins & 11 nominations.", "Genre": "Biography, Comedy, Crime", "tomatoUserMeter": "75", "imdbRating": "7.1", "Language": "English, Spanish", "Country": "USA, Germany, Canada", "BoxOffice": "N/A", "Runtime": "113 min", "tomatoReviews": "159", "imdbID": "tt0270288", "Metascore": "67", "Response": "True", "tomatoURL": "http://www.rottentomatoes.com/m/confessions_of_a_dangerous_mind/", "tomatoRating": "7.2", "Year": "2002"}