{"Plot": "A pair of aging stickup men try to get the old gang back together for one last hurrah before one of the guys takes his last assignment - to kill his comrade.", "Rated": "R", "tomatoImage": "rotten", "Title": "Stand Up Guys", "DVD": "N/A", "tomatoMeter": "37", "Writer": "Noah Haidle", "tomatoUserRating": "3.2", "Production": "N/A", "Actors": "Al Pacino, Christopher Walken, Alan Arkin, Julianna Margulies", "tomatoFresh": "40", "Type": "movie", "imdbVotes": "44,279", "Website": "N/A", "tomatoConsensus": "Stand Up Guys largely wastes its talented cast in a resolutely mediocre comedy hampered by messy direction and a perfunctory script.", "Poster": "http://ia.media-imdb.com/images/M/MV5BMTgwNjgyOTExMV5BMl5BanBnXkFtZTcwNTIzODA1OA@@._V1_SX300.jpg", "tomatoRotten": "67", "Director": "Fisher Stevens", "Released": "01 Feb 2013", "tomatoUserReviews": "18224", "Awards": "N/A", "Genre": "Comedy, Crime, Thriller", "tomatoUserMeter": "46", "imdbRating": "6.5", "Language": "English, Belarusian", "Country": "USA", "BoxOffice": "N/A", "Runtime": "95 min", "tomatoReviews": "107", "imdbID": "tt1389096", "Metascore": "41", "Response": "True", "tomatoURL": "http://www.rottentomatoes.com/m/stand_up_guys/", "tomatoRating": "5.2", "Year": "2012"}