{"Plot": "A porter and a top-model have to pretend to be a couple in order to salvage a CEO's marriage.", "Rated": "PG-13", "tomatoImage": "fresh", "Title": "The Valet", "DVD": "18 Sep 2007", "tomatoMeter": "70", "Writer": "Francis Veber", "tomatoUserRating": "3.5", "Production": "Sony Pictures Classics", "Actors": "Gad Elmaleh, Alice Taglioni, Daniel Auteuil, Kristin Scott Thomas", "tomatoFresh": "57", "Type": "movie", "imdbVotes": "8,011", "Website": "http://www.sonyclassics.com/thevalet", "tomatoConsensus": "Like much of director Francis Veber's work, The Valet is a witty, madcap farce with memorably zany characters.", "Poster": "http://ia.media-imdb.com/images/M/MV5BMTQ5MjM1MjY4NV5BMl5BanBnXkFtZTcwOTM3NzM0MQ@@._V1_SX300.jpg", "tomatoRotten": "24", "Director": "Francis Veber", "Released": "01 Jun 2007", "tomatoUserReviews": "9161", "Awards": "1 win & 1 nomination.", "Genre": "Comedy, Drama", "tomatoUserMeter": "68", "imdbRating": "6.6", "Language": "French", "Country": "France, Italy, Belgium", "BoxOffice": "$2.2M", "Runtime": "85 min", "tomatoReviews": "81", "imdbID": "tt0449851", "Metascore": "68", "Response": "True", "tomatoURL": "http://www.rottentomatoes.com/m/the_valet/", "tomatoRating": "6.6", "Year": "2006"}