{"Plot": "A drama set in New Mexico during WWII, centered on the relationship between a young man and an elderly medicine woman who helps him contend with the battle between good and evil that rages in his village.", "Rated": "PG-13", "tomatoImage": "fresh", "Title": "Bless Me, Ultima", "DVD": "17 Sep 2013", "tomatoMeter": "71", "Writer": "Rudolfo Anaya (based on the novel by), Carl Franklin (written for the screen by)", "tomatoUserRating": "3.8", "Production": "Arenas Entertainment", "Actors": "Luke Ganalon, Miriam Colon, Benito Martinez, Dolores Heredia", "tomatoFresh": "24", "Type": "movie", "imdbVotes": "1,002", "Website": "http://blessmeultima.com/", "tomatoConsensus": "N/A", "Poster": "http://ia.media-imdb.com/images/M/MV5BMTc4MzM0NDkxNl5BMl5BanBnXkFtZTcwNDUwMzk0OA@@._V1_SX300.jpg", "tomatoRotten": "10", "Director": "Carl Franklin", "Released": "22 Feb 2013", "tomatoUserReviews": "1829", "Awards": "3 wins.", "Genre": "Drama, War", "tomatoUserMeter": "73", "imdbRating": "6.5", "Language": "English, Spanish", "Country": "USA", "BoxOffice": "$1.6M", "Runtime": "106 min", "tomatoReviews": "34", "imdbID": "tt1390398", "Metascore": "65", "Response": "True", "tomatoURL": "http://www.rottentomatoes.com/m/bless_me_ultima_2012/", "tomatoRating": "6.1", "Year": "2013"}