{"Plot": "A banished hero of Rome allies with a sworn enemy to take his revenge on the city.", "Rated": "R", "tomatoImage": "certified", "Title": "Coriolanus", "DVD": "29 May 2012", "tomatoMeter": "93", "Writer": "John Logan (screenplay), William Shakespeare (play)", "tomatoUserRating": "3.3", "Production": "The Weinstein Company", "Actors": "Gerard Butler, Ralph Fiennes, Lubna Azabal, Ashraf Barhom", "tomatoFresh": "126", "Type": "movie", "imdbVotes": "26,605", "Website": "http://weinsteinco.com/sites/coriolanus/", "tomatoConsensus": "Visceral and visually striking, Ralph Fiennes' Coriolanus proves Shakespeare can still be both electrifying and relevant in a modern context.", "Poster": "http://ia.media-imdb.com/images/M/MV5BMTcyMjAwMjA2N15BMl5BanBnXkFtZTcwOTI0MjA0Ng@@._V1_SX300.jpg", "tomatoRotten": "10", "Director": "Ralph Fiennes", "Released": "20 Jan 2012", "tomatoUserReviews": "13303", "Awards": "Nominated for 1 BAFTA Film Award. Another 10 wins & 16 nominations.", "Genre": "Drama, Thriller, War", "tomatoUserMeter": "58", "imdbRating": "6.2", "Language": "English", "Country": "UK", "BoxOffice": "N/A", "Runtime": "123 min", "tomatoReviews": "136", "imdbID": "tt1372686", "Metascore": "79", "Response": "True", "tomatoURL": "http://www.rottentomatoes.com/m/coriolanus_2010/", "tomatoRating": "7.4", "Year": "2011"}