{"Plot": "The true story of Captain Richard Phillips and the 2009 hijacking by Somali pirates of the US-flagged MV Maersk Alabama, the first American cargo ship to be hijacked in two hundred years.", "Rated": "PG-13", "tomatoImage": "certified", "Title": "Captain Phillips", "DVD": "21 Jan 2014", "tomatoMeter": "93", "Writer": "Billy Ray (screenplay), Richard Phillips (based upon the book \"A Captain's Duty: Somali Pirates,  Navy SEALS,  and Dangerous Days at Sea\" by), Stephan Talty (based upon the book \"A Captain's Duty: Somali Pirates,  Navy SEALS,  and Dangerous Days at Sea\" by)", "tomatoUserRating": "4.2", "Production": "Sony Pictures", "Actors": "Tom Hanks, Catherine Keener, Barkhad Abdi, Barkhad Abdirahman", "tomatoFresh": "225", "Type": "movie", "imdbVotes": "316,246", "Website": "http://www.captainphillipsmovie.com/", "tomatoConsensus": "Smart, powerfully acted, and incredibly intense, Captain Phillips offers filmgoers a Hollywood biopic done right -- and offers Tom Hanks a showcase for yet another brilliant performance.", "Poster": "http://ia.media-imdb.com/images/M/MV5BMTQzNzExMDg3Ml5BMl5BanBnXkFtZTgwODU1NzEzMDE@._V1_SX300.jpg", "tomatoRotten": "17", "Director": "Paul Greengrass", "Released": "11 Oct 2013", "tomatoUserReviews": "150542", "Awards": "Nominated for 6 Oscars. Another 16 wins & 135 nominations.", "Genre": "Biography, Drama, Thriller", "tomatoUserMeter": "89", "imdbRating": "7.9", "Language": "Somali, English", "Country": "USA", "BoxOffice": "$107.1M", "Runtime": "134 min", "tomatoReviews": "242", "imdbID": "tt1535109", "Metascore": "83", "Response": "True", "tomatoURL": "http://www.rottentomatoes.com/m/captain_phillips/", "tomatoRating": "8.3", "Year": "2013"}