{"Plot": "Disgraced Secret Service agent (and former presidential guard) Mike Banning finds himself trapped inside the White House in the wake of a terrorist attack; using his inside knowledge, Banning works with national security to rescue the President from his kidnappers.", "Rated": "R", "tomatoImage": "rotten", "Title": "Olympus Has Fallen", "DVD": "13 Aug 2013", "tomatoMeter": "47", "Writer": "Creighton Rothenberger, Katrin Benedikt", "tomatoUserRating": "3.7", "Production": "FilmDistrict", "Actors": "Gerard Butler, Aaron Eckhart, Finley Jacobsen, Dylan McDermott", "tomatoFresh": "86", "Type": "movie", "imdbVotes": "196,159", "Website": "http://olympusmovie.com", "tomatoConsensus": "It's far from original, but Olympus Has Fallen benefits from Antoine Fuqua's tense direction and a strong performance from Gerard Butler -- which might just be enough for action junkies.", "Poster": "http://ia.media-imdb.com/images/M/MV5BMTkxNjIyNjE5OF5BMl5BanBnXkFtZTcwMTI3NzkxOQ@@._V1_SX300.jpg", "tomatoRotten": "96", "Director": "Antoine Fuqua", "Released": "22 Mar 2013", "tomatoUserReviews": "147736", "Awards": "1 win & 5 nominations.", "Genre": "Action, Thriller", "tomatoUserMeter": "67", "imdbRating": "6.5", "Language": "Korean, English", "Country": "USA", "BoxOffice": "$98.6M", "Runtime": "119 min", "tomatoReviews": "182", "imdbID": "tt2302755", "Metascore": "41", "Response": "True", "tomatoURL": "http://www.rottentomatoes.com/m/olympus_has_fallen_2013/", "tomatoRating": "5.3", "Year": "2013"}