{"Plot": "After a bad blind date, a man and woman find themselves stuck together at a resort for families, where their attraction grows as their respective kids benefit from the burgeoning relationship.", "Rated": "PG-13", "tomatoImage": "rotten", "Title": "Blended", "DVD": "26 Aug 2014", "tomatoMeter": "14", "Writer": "Ivan Menchell, Clare Sera", "tomatoUserRating": "3.6", "Production": "Warner Bros. Pictures", "Actors": "Adam Sandler, Drew Barrymore, Kevin Nealon, Terry Crews", "tomatoFresh": "18", "Type": "movie", "imdbVotes": "84,222", "Website": "http://blendedmovie.com/", "tomatoConsensus": "Lurching between slapstick and schmaltz without showing much of a commitment to either, Blended commits the rare Sandler sin of provoking little more than boredom.", "Poster": "http://ia.media-imdb.com/images/M/MV5BNzc2ODI5NjAyMl5BMl5BanBnXkFtZTgwMzIyOTE4MDE@._V1_SX300.jpg", "tomatoRotten": "112", "Director": "Frank Coraci", "Released": "23 May 2014", "tomatoUserReviews": "52610", "Awards": "1 win & 10 nominations.", "Genre": "Comedy, Romance", "tomatoUserMeter": "64", "imdbRating": "6.5", "Language": "English", "Country": "USA", "BoxOffice": "N/A", "Runtime": "117 min", "tomatoReviews": "130", "imdbID": "tt1086772", "Metascore": "31", "Response": "True", "tomatoURL": "http://www.rottentomatoes.com/m/blended/", "tomatoRating": "3.9", "Year": "2014"}