{"Plot": "A romantic comedy about an Englishman brought in to help unmask a possible swindle. Personal and professional complications ensue.", "Rated": "PG-13", "tomatoImage": "rotten", "Title": "Magic in the Moonlight", "DVD": "16 Dec 2014", "tomatoMeter": "52", "Writer": "Woody Allen", "tomatoUserRating": "3.2", "Production": "Sony Pictures Classics", "Actors": "Colin Firth, Antonia Clarke, Natasha Andrews, Val\u00e9rie Beaulieu", "tomatoFresh": "82", "Type": "movie", "imdbVotes": "43,104", "Website": "http://sonyclassics.com/magicinthemoonlight/", "tomatoConsensus": "While far from a failure, Magic in the Moonlight is too slight to stand with Woody Allen's finest work.", "Poster": "http://ia.media-imdb.com/images/M/MV5BMTQ3NDY5NjIwN15BMl5BanBnXkFtZTgwNjQ2ODkxMjE@._V1_SX300.jpg", "tomatoRotten": "77", "Director": "Woody Allen", "Released": "15 Aug 2014", "tomatoUserReviews": "12074", "Awards": "1 win & 1 nomination.", "Genre": "Comedy, Romance", "tomatoUserMeter": "45", "imdbRating": "6.6", "Language": "English", "Country": "USA, UK", "BoxOffice": "N/A", "Runtime": "97 min", "tomatoReviews": "159", "imdbID": "tt2870756", "Metascore": "54", "Response": "True", "tomatoURL": "http://www.rottentomatoes.com/m/magic_in_the_moonlight/", "tomatoRating": "5.8", "Year": "2014"}