{"Plot": "Four weeks after a mysterious, incurable virus spreads throughout the UK, a handful of survivors try to find sanctuary.", "Rated": "R", "tomatoImage": "certified", "Title": "28 Days Later...", "DVD": "21 Oct 2003", "tomatoMeter": "87", "Writer": "Alex Garland", "tomatoUserRating": "3.6", "Production": "Fox Searchlight Pictures", "Actors": "Alex Palmer, Bindu De Stoppani, Jukka Hiltunen, David Schneider", "tomatoFresh": "190", "Type": "movie", "imdbVotes": "289,928", "Website": "http://www.28dayslaterthemovie.co.uk/main.html", "tomatoConsensus": "Kinetically directed by Danny Boyle, 28 Days Later is both a terrifying zombie movie and a sharp political allegory.", "Poster": "http://ia.media-imdb.com/images/M/MV5BMTk3NjEwNDMzMF5BMl5BanBnXkFtZTgwMzgwNDgwNzE@._V1_SX300.jpg", "tomatoRotten": "29", "Director": "Danny Boyle", "Released": "27 Jun 2003", "tomatoUserReviews": "480106", "Awards": "9 wins & 26 nominations.", "Genre": "Horror, Sci-Fi, Thriller", "tomatoUserMeter": "85", "imdbRating": "7.6", "Language": "English, Spanish", "Country": "UK", "BoxOffice": "$44.9M", "Runtime": "113 min", "tomatoReviews": "219", "imdbID": "tt0289043", "Metascore": "73", "Response": "True", "tomatoURL": "http://www.rottentomatoes.com/m/28_days_later/", "tomatoRating": "7.4", "Year": "2002"}