{"Plot": "An ambitious but troubled movie director tries his best to fulfill his dream, despite his lack of support.", "Rated": "R", "tomatoImage": "certified", "Title": "Ed Wood", "DVD": "13 Aug 2002", "tomatoMeter": "92", "Writer": "Rudolph Grey (book), Scott Alexander, Larry Karaszewski", "tomatoUserRating": "3.8", "Production": "Buena Vista Pictures", "Actors": "Johnny Depp, Martin Landau, Sarah Jessica Parker, Patricia Arquette", "tomatoFresh": "55", "Type": "movie", "imdbVotes": "140,594", "Website": "N/A", "tomatoConsensus": "Tim Burton and Johnny Depp team up to fete the life and work of cult hero Ed Wood, with typically strange and wonderful results.", "Poster": "http://ia.media-imdb.com/images/M/MV5BMjAzODM1MDMxN15BMl5BanBnXkFtZTgwOTgwNTc2MDE@._V1_SX300.jpg", "tomatoRotten": "5", "Director": "Tim Burton", "Released": "07 Oct 1994", "tomatoUserReviews": "106451", "Awards": "Won 2 Oscars. Another 22 wins & 15 nominations.", "Genre": "Biography, Comedy, Drama", "tomatoUserMeter": "88", "imdbRating": "7.9", "Language": "English", "Country": "USA", "BoxOffice": "N/A", "Runtime": "127 min", "tomatoReviews": "60", "imdbID": "tt0109707", "Metascore": "70", "Response": "True", "tomatoURL": "http://www.rottentomatoes.com/m/ed_wood/", "tomatoRating": "8.0", "Year": "1994"}