{"Plot": "Balian of Ibelin travels to Jerusalem during the crusades of the 12th century, and there he finds himself as the defender of the city and its people.", "Rated": "R", "tomatoImage": "rotten", "Title": "Kingdom of Heaven", "DVD": "11 Oct 2005", "tomatoMeter": "39", "Writer": "William Monahan", "tomatoUserRating": "3.4", "Production": "20th Century Fox", "Actors": "Martin Hancock, Michael Sheen, Nathalie Cox, Eriq Ebouaney", "tomatoFresh": "72", "Type": "movie", "imdbVotes": "213,795", "Website": "http://www.kingdomofheavenmovie.com/", "tomatoConsensus": "Although it's an objective and handsomely presented take on the Crusades, Kingdom of Heaven lacks depth.", "Poster": "http://ia.media-imdb.com/images/M/MV5BMjE2MTIwNjg0MV5BMl5BanBnXkFtZTcwNjAxODIzMw@@._V1_SX300.jpg", "tomatoRotten": "114", "Director": "Ridley Scott", "Released": "06 May 2005", "tomatoUserReviews": "364633", "Awards": "4 wins & 13 nominations.", "Genre": "Action, Adventure, Drama", "tomatoUserMeter": "72", "imdbRating": "7.2", "Language": "English, Arabic, Italian, Latin", "Country": "USA, UK, Spain, Germany, Morocco", "BoxOffice": "$47.3M", "Runtime": "144 min", "tomatoReviews": "186", "imdbID": "tt0320661", "Metascore": "63", "Response": "True", "tomatoURL": "http://www.rottentomatoes.com/m/kingdom_of_heaven/", "tomatoRating": "5.6", "Year": "2005"}