{"Plot": "A writer who is brutalized during her cabin retreat seeks revenge on her attackers, who left her for dead.", "Rated": "R", "tomatoImage": "rotten", "Title": "I Spit on Your Grave", "DVD": "08 Feb 2011", "tomatoMeter": "34", "Writer": "Adam Rockoff (screenplay), Meir Zarchi (film: Day of the Woman)", "tomatoUserRating": "3.1", "Production": "Anchor Bay Films", "Actors": "Sarah Butler, Jeff Branson, Andrew Howard, Daniel Franzese", "tomatoFresh": "19", "Type": "movie", "imdbVotes": "54,565", "Website": "http://www.ispitonyourgravemovie.com/", "tomatoConsensus": "N/A", "Poster": "http://ia.media-imdb.com/images/M/MV5BMTkxMTE3NzEzMl5BMl5BanBnXkFtZTcwMzc4MTU2Mw@@._V1_SX300.jpg", "tomatoRotten": "37", "Director": "Steven R. Monroe", "Released": "20 Jan 2011", "tomatoUserReviews": "10431", "Awards": "2 nominations.", "Genre": "Crime, Horror", "tomatoUserMeter": "48", "imdbRating": "6.3", "Language": "English", "Country": "USA", "BoxOffice": "$92.4k", "Runtime": "108 min", "tomatoReviews": "56", "imdbID": "tt1242432", "Metascore": "27", "Response": "True", "tomatoURL": "http://www.rottentomatoes.com/m/i_spit_on_your_grave_2010/", "tomatoRating": "4.4", "Year": "2010"}