{"Plot": "Basquiat tells the story of the meteoric rise of youthful artist Jean-Michel Basquiat. Starting out as a street artist, living in Thompkins Square Park in a cardboard box, Jean-Michel is \"...", "Rated": "R", "tomatoImage": "N/A", "Title": "Basquiat", "DVD": "11 Oct 2005", "tomatoMeter": "N/A", "Writer": "Lech Majewski (story), John Bowe (short story), Julian Schnabel, Michael Holman (story development)", "tomatoUserRating": "2.2", "Production": "N/A", "Actors": "Jeffrey Wright, Michael Wincott, Benicio Del Toro, Claire Forlani", "tomatoFresh": "N/A", "Type": "movie", "imdbVotes": "15,607", "Website": "N/A", "tomatoConsensus": "N/A", "Poster": "http://ia.media-imdb.com/images/M/MV5BMTY4NDY1NzkxN15BMl5BanBnXkFtZTYwMDkwMzE5._V1_SX300.jpg", "tomatoRotten": "N/A", "Director": "Julian Schnabel", "Released": "09 Aug 1996", "tomatoUserReviews": "78", "Awards": "2 wins & 3 nominations.", "Genre": "Biography, Drama", "tomatoUserMeter": "20", "imdbRating": "6.9", "Language": "English, Spanish", "Country": "USA", "BoxOffice": "N/A", "Runtime": "108 min", "tomatoReviews": "N/A", "imdbID": "tt0115632", "Metascore": "65", "Response": "True", "tomatoURL": "http://www.rottentomatoes.com/m/nocne_graffiti_1996/", "tomatoRating": "N/A", "Year": "1996"}