{"Plot": "In order to save their home from foreclosure, a group of misfits set out to find a pirate's ancient treasure.", "Rated": "PG", "tomatoImage": "fresh", "Title": "The Goonies", "DVD": "21 Aug 2001", "tomatoMeter": "69", "Writer": "Steven Spielberg (story), Chris Columbus (screenplay)", "tomatoUserRating": "3.8", "Production": "Amblin Entertainment", "Actors": "Sean Astin, Josh Brolin, Jeff Cohen, Corey Feldman", "tomatoFresh": "31", "Type": "movie", "imdbVotes": "174,205", "Website": "N/A", "tomatoConsensus": "An energetic, sometimes noisy mix of Speilbergian sentiment and funhouse tricks that will appeal to kids and nostalgic adults alike.", "Poster": "http://ia.media-imdb.com/images/M/MV5BMTEyMzM3NDQyMjJeQTJeQWpwZ15BbWU4MDE4ODY0NjEx._V1_SX300.jpg", "tomatoRotten": "14", "Director": "Richard Donner", "Released": "07 Jun 1985", "tomatoUserReviews": "577546", "Awards": "2 wins & 6 nominations.", "Genre": "Adventure, Comedy, Family", "tomatoUserMeter": "91", "imdbRating": "7.8", "Language": "Cantonese, English, Italian, Spanish", "Country": "USA", "BoxOffice": "N/A", "Runtime": "114 min", "tomatoReviews": "45", "imdbID": "tt0089218", "Metascore": "60", "Response": "True", "tomatoURL": "http://www.rottentomatoes.com/m/goonies/", "tomatoRating": "6.1", "Year": "1985"}