{"Plot": "Three trappers protect a British Colonel's daughters in the midst of the French and Indian War.", "Rated": "R", "tomatoImage": "fresh", "Title": "The Last of the Mohicans", "DVD": "23 Nov 1999", "tomatoMeter": "94", "Writer": "James Fenimore Cooper (novel), John L. Balderston (adaptation), Paul Perez (adaptation), Daniel Moore (adaptation), Philip Dunne, Michael Mann (screenplay), Christopher Crowe (screenplay)", "tomatoUserRating": "3.6", "Production": "Twentieth Century Fox Home Entertainment", "Actors": "Daniel Day-Lewis, Madeleine Stowe, Russell Means, Eric Schweig", "tomatoFresh": "34", "Type": "movie", "imdbVotes": "110,738", "Website": "N/A", "tomatoConsensus": "N/A", "Poster": "http://ia.media-imdb.com/images/M/MV5BMTQ0MjQ5NDAzMV5BMl5BanBnXkFtZTcwNjYzMjE2MQ@@._V1_SX300.jpg", "tomatoRotten": "2", "Director": "Michael Mann", "Released": "25 Sep 1992", "tomatoUserReviews": "206604", "Awards": "Won 1 Oscar. Another 5 wins & 13 nominations.", "Genre": "Action, Adventure, Drama", "tomatoUserMeter": "88", "imdbRating": "7.8", "Language": "English, French, Mohawk", "Country": "USA", "BoxOffice": "N/A", "Runtime": "112 min", "tomatoReviews": "36", "imdbID": "tt0104691", "Metascore": "76", "Response": "True", "tomatoURL": "http://www.rottentomatoes.com/m/1040678-last_of_the_mohicans/", "tomatoRating": "7.9", "Year": "1992"}