{"Plot": "Heidi, a radio DJ, is sent a box containing a record - a \"gift from the Lords\". The sounds within the grooves trigger flashbacks of her town's violent past. Is Heidi going mad, or are the Lords back to take revenge on Salem, Massachusetts?", "Rated": "R", "tomatoImage": "rotten", "Title": "The Lords of Salem", "DVD": "03 Sep 2013", "tomatoMeter": "45", "Writer": "Rob Zombie", "tomatoUserRating": "2.5", "Production": "Anchor Bay Films", "Actors": "Sheri Moon Zombie, Bruce Davison, Jeff Daniel Phillips, Judy Geeson", "tomatoFresh": "26", "Type": "movie", "imdbVotes": "19,645", "Website": "http://www.lordsofsalem.com/", "tomatoConsensus": "The Lords of Salem has lots of atmospheric portent, but it's unfortunately short on scares.", "Poster": "http://ia.media-imdb.com/images/M/MV5BMjA2NTc5Njc4MV5BMl5BanBnXkFtZTcwNTYzMTcwOQ@@._V1_SX300.jpg", "tomatoRotten": "32", "Director": "Rob Zombie", "Released": "18 Apr 2013", "tomatoUserReviews": "13620", "Awards": "1 win & 3 nominations.", "Genre": "Horror, Thriller", "tomatoUserMeter": "30", "imdbRating": "5.1", "Language": "English", "Country": "USA, UK, Canada", "BoxOffice": "$1.0M", "Runtime": "101 min", "tomatoReviews": "58", "imdbID": "tt1731697", "Metascore": "57", "Response": "True", "tomatoURL": "http://www.rottentomatoes.com/m/the_lords_of_salem/", "tomatoRating": "5.3", "Year": "2012"}