{"Plot": "In a world of fake castles and anthropomorphic rodents, an epic battle begins when an unemployed father's sanity is challenged by a chance encounter with two underage girls on holiday.", "Rated": "NOT RATED", "tomatoImage": "rotten", "Title": "Escape from Tomorrow", "DVD": "29 Apr 2014", "tomatoMeter": "56", "Writer": "Randy Moore", "tomatoUserRating": "2.5", "Production": "FilmBuff", "Actors": "Roy Abramsohn, Elena Schuber, Katelynn Rodriguez, Jack Dalton", "tomatoFresh": "44", "Type": "movie", "imdbVotes": "7,206", "Website": "http://www.escape-from-tomorrow.com/", "tomatoConsensus": "Conceptually audacious but only intermittently successful in execution, Escape From Tomorrow is nonetheless visually inventive and darkly surreal.", "Poster": "http://ia.media-imdb.com/images/M/MV5BNTIxNjcxOTgxM15BMl5BanBnXkFtZTgwMjYzODEzMDE@._V1_SX300.jpg", "tomatoRotten": "34", "Director": "Randy Moore", "Released": "19 Jul 2014", "tomatoUserReviews": "6723", "Awards": "2 wins & 4 nominations.", "Genre": "Fantasy, Horror", "tomatoUserMeter": "26", "imdbRating": "5.2", "Language": "French, English", "Country": "USA", "BoxOffice": "$0.2M", "Runtime": "90 min", "tomatoReviews": "78", "imdbID": "tt2187884", "Metascore": "58", "Response": "True", "tomatoURL": "http://www.rottentomatoes.com/m/escape_from_tomorrow_2013/", "tomatoRating": "6.1", "Year": "2013"}