{"Plot": "A man who escapes from the vicious grips of the serial killer known as \"The Collector\" is blackmailed to rescue an innocent girl from the killer's booby-trapped warehouse.", "Rated": "R", "tomatoImage": "rotten", "Title": "The Collection", "DVD": "26 Mar 2013", "tomatoMeter": "37", "Writer": "Patrick Melton, Marcus Dunstan, Patrick Melton (characters), Marcus Dunstan (characters)", "tomatoUserRating": "3.3", "Production": "LD Entertainment", "Actors": "Josh Stewart, Emma Fitzpatrick, Christopher McDonald, Lee Tergesen", "tomatoFresh": "18", "Type": "movie", "imdbVotes": "35,377", "Website": "http://www.thecollectionmovie.com/", "tomatoConsensus": "The Collection offers more grisly thrills and twisted humor than its predecessor; in other words, fun for genre fans, but unpleasant for anyone else.", "Poster": "http://ia.media-imdb.com/images/M/MV5BODQ0MDgzNDA0NV5BMl5BanBnXkFtZTcwNDM4MDQ1OA@@._V1_SX300.jpg", "tomatoRotten": "31", "Director": "Marcus Dunstan", "Released": "30 Nov 2012", "tomatoUserReviews": "19223", "Awards": "N/A", "Genre": "Action, Horror, Thriller", "tomatoUserMeter": "50", "imdbRating": "6.1", "Language": "English", "Country": "USA", "BoxOffice": "$6.8M", "Runtime": "82 min", "tomatoReviews": "49", "imdbID": "tt1748227", "Metascore": "36", "Response": "True", "tomatoURL": "http://www.rottentomatoes.com/m/the_collection_2012/", "tomatoRating": "4.1", "Year": "2012"}