{"Plot": "A young female intern at a small magazine company becomes involved with a drug-addicted lesbian photographer, both of whom seek to exploit each other for their respective careers, while slowly falling in love with each other.", "Rated": "R", "tomatoImage": "fresh", "Title": "High Art", "DVD": "27 Jul 2004", "tomatoMeter": "72", "Writer": "Lisa Cholodenko", "tomatoUserRating": "3.7", "Production": "October Releasing", "Actors": "Radha Mitchell, Gabriel Mann, Charis Michelsen, David Thornton", "tomatoFresh": "31", "Type": "movie", "imdbVotes": "8,259", "Website": "N/A", "tomatoConsensus": "N/A", "Poster": "http://ia.media-imdb.com/images/M/MV5BMjAyMjIwMzM3M15BMl5BanBnXkFtZTcwOTU0MDYyMQ@@._V1_SX300.jpg", "tomatoRotten": "12", "Director": "Lisa Cholodenko", "Released": "12 Jun 1998", "tomatoUserReviews": "8063", "Awards": "7 wins & 17 nominations.", "Genre": "Drama, Romance", "tomatoUserMeter": "77", "imdbRating": "6.7", "Language": "English", "Country": "USA", "BoxOffice": "N/A", "Runtime": "101 min", "tomatoReviews": "43", "imdbID": "tt0139362", "Metascore": "73", "Response": "True", "tomatoURL": "http://www.rottentomatoes.com/m/high_art/", "tomatoRating": "6.8", "Year": "1998"}