{"Plot": "A father goes undercover for the DEA in order to free his son who was imprisoned after being set up in drug deal.", "Rated": "PG-13", "tomatoImage": "rotten", "Title": "Snitch", "DVD": "11 Jun 2013", "tomatoMeter": "56", "Writer": "Justin Haythe, Ric Roman Waugh", "tomatoUserRating": "3.6", "Production": "Lionsgate//Summit Entertainment", "Actors": "Dwayne Johnson, Barry Pepper, Jon Bernthal, Susan Sarandon", "tomatoFresh": "79", "Type": "movie", "imdbVotes": "63,449", "Website": "http://www.snitch-movie.com", "tomatoConsensus": "Though it features one of Dwayne Johnson's more thoughtful performances, the presentation of Snitch's underlying message is muddled by lackluster storytelling and some tonal inconsistencies.", "Poster": "http://ia.media-imdb.com/images/M/MV5BNTM4MTYzNjA3Nl5BMl5BanBnXkFtZTcwMzcyNDA5OA@@._V1_SX300.jpg", "tomatoRotten": "62", "Director": "Ric Roman Waugh", "Released": "22 Feb 2013", "tomatoUserReviews": "63280", "Awards": "1 nomination.", "Genre": "Action, Drama, Thriller", "tomatoUserMeter": "61", "imdbRating": "6.5", "Language": "English, Spanish", "Country": "USA, United Arab Emirates", "BoxOffice": "$42.9M", "Runtime": "112 min", "tomatoReviews": "141", "imdbID": "tt0882977", "Metascore": "51", "Response": "True", "tomatoURL": "http://www.rottentomatoes.com/m/snitch_2013/", "tomatoRating": "5.6", "Year": "2013"}