{"Plot": "A British college student falls for an American student, only to be separated from him when she's banned from the U.S. after overstaying her visa.", "Rated": "PG-13", "tomatoImage": "certified", "Title": "Like Crazy", "DVD": "06 Mar 2012", "tomatoMeter": "72", "Writer": "Drake Doremus, Ben York Jones", "tomatoUserRating": "3.4", "Production": "Paramount Pictures", "Actors": "Anton Yelchin, Felicity Jones, Jennifer Lawrence, Charlie Bewley", "tomatoFresh": "105", "Type": "movie", "imdbVotes": "45,277", "Website": "http://www.likecrazy.com/", "tomatoConsensus": "It has the schmaltzy trappings of my romantic films, but Like Crazy allows its characters to express themselves beyond dialogue, crafting a true, intimate study.", "Poster": "http://ia.media-imdb.com/images/M/MV5BMjAzOTgyOTU4OF5BMl5BanBnXkFtZTcwNDYxMjcxNg@@._V1_SX300.jpg", "tomatoRotten": "41", "Director": "Drake Doremus", "Released": "27 Jan 2012", "tomatoUserReviews": "18838", "Awards": "9 wins & 6 nominations.", "Genre": "Drama, Romance", "tomatoUserMeter": "61", "imdbRating": "6.7", "Language": "English", "Country": "USA", "BoxOffice": "$3.4M", "Runtime": "90 min", "tomatoReviews": "146", "imdbID": "tt1758692", "Metascore": "71", "Response": "True", "tomatoURL": "http://www.rottentomatoes.com/m/like_crazy/", "tomatoRating": "6.5", "Year": "2011"}